regina_normalizer/__init__.py
regina_normalizer/abbr_dict.py
regina_normalizer/abbr_functions.py
regina_normalizer/abbr_patterns.py
regina_normalizer/abbreviations_general.txt
regina_normalizer/abbreviations_nonending.txt
regina_normalizer/area_dict.py
regina_normalizer/cardinal_big_tuples.py
regina_normalizer/cardinal_million_tuples.py
regina_normalizer/cardinal_ones_tuples.py
regina_normalizer/cardinal_thousands_tuples.py
regina_normalizer/currency_dict.py
regina_normalizer/decimal_thousands_tuples.py
regina_normalizer/denominator_dict.py
regina_normalizer/direction_dict.py
regina_normalizer/distance_dict.py
regina_normalizer/electronic_dict.py
regina_normalizer/fraction_tuples.py
regina_normalizer/normalizer.py
regina_normalizer/number_functions.py
regina_normalizer/number_help.py
regina_normalizer/number_patterns.py
regina_normalizer/ordinal_big_tuples.py
regina_normalizer/ordinal_million_tuples.py
regina_normalizer/ordinal_ones_tuples.py
regina_normalizer/ordinal_thousands_tuples.py
regina_normalizer/period_dict.py
regina_normalizer/pre_help_dicts.py
regina_normalizer/rest_dict.py
regina_normalizer/sport_tuples.py
regina_normalizer/symbols_dict.py
regina_normalizer/time_dict.py
regina_normalizer/time_tuples.py
regina_normalizer/tokenizer.py
regina_normalizer/tuple_rules.py
regina_normalizer/volume_dict.py
regina_normalizer/weight_dict.py
regina_normalizer-0.0.6.dist-info/LICENSE
regina_normalizer-0.0.6.dist-info/METADATA
regina_normalizer-0.0.6.dist-info/WHEEL
regina_normalizer-0.0.6.dist-info/entry_points.txt
regina_normalizer-0.0.6.dist-info/top_level.txt
regina_normalizer-0.0.6.dist-info/RECORD
