Metadata-Version: 2.1
Name: regina-normalizer
Version: 0.0.6
Summary: A text normalization package for Icelandic
Home-page: https://github.com/cadia-lvl/regina-normalizer/tree/master/regina_package
Author: Helga Svala Sigurðardóttir, Anna Björk Nikulásdóttir
Author-email: helgas@ru.is
License: MIT
Platform: UNKNOWN
Requires-Python: >=3.5
License-File: LICENSE
Requires-Dist: setuptools
Requires-Dist: wandb
